dayiwasborn/__init__.py
dayiwasborn/cli.py
dayiwasborn/dayiwasborn.py
dayiwasborn-0.3.1.dist-info/METADATA
dayiwasborn-0.3.1.dist-info/RECORD
dayiwasborn-0.3.1.dist-info/WHEEL
dayiwasborn-0.3.1.dist-info/entry_points.txt
dayiwasborn-0.3.1.dist-info/top_level.txt
