Metadata-Version: 2.1
Name: dayiwasborn
Version: 0.3.1
Summary: Tell us the date, and we'll tell you the weekday!
Home-page: https://github.com/eliasdabbas/dayiwasborn
Author: Elias Dabbas
Author-email: eliasdabbas@gmail.com
License: MIT license
Keywords: dayiwasborn
Platform: UNKNOWN
Classifier: Development Status :: 2 - Pre-Alpha
Classifier: Intended Audience :: Developers
Classifier: License :: OSI Approved :: MIT License
Classifier: Natural Language :: English
Classifier: Programming Language :: Python :: 2
Classifier: Programming Language :: Python :: 2.7
Classifier: Programming Language :: Python :: 3
Classifier: Programming Language :: Python :: 3.4
Classifier: Programming Language :: Python :: 3.5
Classifier: Programming Language :: Python :: 3.6
Requires-Dist: Click (>=6.0)
